lcc2json/__init__.py
lcc2json/_version.py
lcc2json/download.py
lcc2json/lcc2json.py
lcc2json-1.4.0.dist-info/licenses/LICENSE-apache.txt
lcc2json-1.4.0.dist-info/METADATA
lcc2json-1.4.0.dist-info/WHEEL
lcc2json-1.4.0.dist-info/entry_points.txt
lcc2json-1.4.0.dist-info/top_level.txt
lcc2json-1.4.0.dist-info/RECORD
