Metadata-Version: 2.4
Name: lcc2json
Version: 1.4.0
Summary: Creates a JSON file of the Library of Congress Classification system
Author-email: Jeff Moe <moe@spacecruft.org>
License: Apache 2.0
Project-URL: Homepage, https://spacecruft.org/books/lcc2json
Project-URL: Documentation, https://spacecruft.org/books/lcc2json
Project-URL: Repository, https://spacecruft.org/books/lcc2json
Project-URL: Issues, https://spacecruft.org/books/lcc2json
Project-URL: Changelog, https://spacecruft.org/books/lcc2json/raw/branch/main/CHANGELOG.txt
Classifier: Development Status :: 5 - Production/Stable
Classifier: Environment :: Console
Classifier: Intended Audience :: Developers
Classifier: Intended Audience :: Information Technology
Classifier: License :: OSI Approved :: Apache Software License
Classifier: Natural Language :: English
Classifier: Operating System :: POSIX :: Linux
Classifier: Programming Language :: Python :: 3
Classifier: Topic :: Education
Classifier: Topic :: File Formats :: JSON
Classifier: Topic :: Text Processing :: Indexing
Requires-Python: >=3.11
License-File: LICENSE-apache.txt
Requires-Dist: pydantic
Requires-Dist: requests
Provides-Extra: dev
Requires-Dist: black; extra == "dev"
Requires-Dist: build; extra == "dev"
Requires-Dist: flake8==7.*; extra == "dev"
Requires-Dist: flake8-pyproject==1.*; extra == "dev"
Requires-Dist: isort==5.*; extra == "dev"
Requires-Dist: pytest==7.*; extra == "dev"
Requires-Dist: ruff; extra == "dev"
Requires-Dist: setuptools-scm; extra == "dev"
Requires-Dist: twine; extra == "dev"
Dynamic: license-file
